TOPSIS_package/cli.py
topsis_priyank_raheja_101703404-1.0.dist-info/METADATA
topsis_priyank_raheja_101703404-1.0.dist-info/WHEEL
topsis_priyank_raheja_101703404-1.0.dist-info/entry_points.txt
topsis_priyank_raheja_101703404-1.0.dist-info/top_level.txt
topsis_priyank_raheja_101703404-1.0.dist-info/RECORD
