Metadata-Version: 2.1
Name: topsis-priyank-raheja-101703404
Version: 1.0
Summary: Topsis analysis
Home-page: UNKNOWN
Author: priyank raheja
Author-email: praheja_be17@thapar.edu
License: MIT
Platform: UNKNOWN
Classifier: License :: OSI Approved :: MIT License
Classifier: Programming Language :: Python :: 3
Classifier: Programming Language :: Python :: 3.7
Requires-Dist: numpy
Requires-Dist: pandas
